config/__init__.py
config/env_config.py
email_helper/__init__.py
email_helper/config_email.py
utils_packages-0.0.1.dist-info/LICENCE.txt
utils_packages-0.0.1.dist-info/METADATA
utils_packages-0.0.1.dist-info/WHEEL
utils_packages-0.0.1.dist-info/top_level.txt
utils_packages-0.0.1.dist-info/RECORD
