Metadata-Version: 2.1
Name: utils-packages
Version: 0.0.1
Summary: utils packages email
Home-page: 
Author: triandn
Author-email: triandn43@gmail.com
License: MIT
Keywords: utils_email_helper
Classifier: Development Status :: 5 - Production/Stable
Classifier: Intended Audience :: Education
Classifier: Operating System :: Microsoft :: Windows :: Windows 10
Classifier: License :: OSI Approved :: MIT License
Classifier: Programming Language :: Python :: 3
License-File: LICENCE.txt
